MANIFEST.in
setup.py
tests/__init__.py
tests/test_common.py
tests/test_constants.py
tests/test_listitem.py
tests/test_module.py
tests/test_plugin.py
tests/test_request.py
tests/test_storage.py
tests/test_urls.py
tests/test_xbmcmixin.py
tests/utils.py
tests/cli/__init__.py
tests/cli/test_console.py
tests/cli/test_create.py
xbmcswift2/__init__.py
xbmcswift2/actions.py
xbmcswift2/common.py
xbmcswift2/constants.py
xbmcswift2/listitem.py
xbmcswift2/logger.py
xbmcswift2/module.py
xbmcswift2/plugin.py
xbmcswift2/request.py
xbmcswift2/storage.py
xbmcswift2/urls.py
xbmcswift2/xbmcmixin.py
xbmcswift2.egg-info/PKG-INFO
xbmcswift2.egg-info/SOURCES.txt
xbmcswift2.egg-info/dependency_links.txt
xbmcswift2.egg-info/entry_points.txt
xbmcswift2.egg-info/top_level.txt
xbmcswift2/cli/__init__.py
xbmcswift2/cli/app.py
xbmcswift2/cli/cli.py
xbmcswift2/cli/console.py
xbmcswift2/cli/create.py
xbmcswift2/cli/data/addon.py
xbmcswift2/cli/data/addon.xml
xbmcswift2/cli/data/resources/__init__.py
xbmcswift2/cli/data/resources/language/English/strings.xml
xbmcswift2/cli/data/resources/lib/__init__.py
xbmcswift2/ext/__init__.py
xbmcswift2/ext/playlist.py
xbmcswift2/mockxbmc/__init__.py
xbmcswift2/mockxbmc/utils.py
xbmcswift2/mockxbmc/xbmc.py
xbmcswift2/mockxbmc/xbmcaddon.py
xbmcswift2/mockxbmc/xbmcgui.py
xbmcswift2/mockxbmc/xbmcplugin.py
xbmcswift2/mockxbmc/xbmcvfs.py