Metadata-Version: 1.0
Name: xbmcswift2
Version: 0.3.0
Summary: A micro framework for rapid development of XBMC plugins.
Home-page: https://github.com/jbeluch/xbmcswift2
Author: Jonathan Beluch
Author-email: web@jonathanbeluch.com
License: GPL3
Keywords: example documentation tutorial
Platform: UNKNOWN
Classifier: Development Status :: 3 - Alpha
Classifier: Topic :: Utilities
Classifier: License :: OSI Approved :: GNU Affero General Public License v3
Classifier: Programming Language :: Python
